ingestr/conftest.py
ingestr/main.py
ingestr/src/.gitignore
ingestr/src/blob.py
ingestr/src/buildinfo.py
ingestr/src/destinations.py
ingestr/src/errors.py
ingestr/src/factory.py
ingestr/src/filters.py
ingestr/src/http_client.py
ingestr/src/loader.py
ingestr/src/masking.py
ingestr/src/partition.py
ingestr/src/resource.py
ingestr/src/sources.py
ingestr/src/table_definition.py
ingestr/src/time.py
ingestr/src/version.py
ingestr/src/adjust/__init__.py
ingestr/src/adjust/adjust_helpers.py
ingestr/src/airtable/__init__.py
ingestr/src/allium/__init__.py
ingestr/src/anthropic/__init__.py
ingestr/src/anthropic/helpers.py
ingestr/src/applovin/__init__.py
ingestr/src/applovin_max/__init__.py
ingestr/src/appsflyer/__init__.py
ingestr/src/appsflyer/client.py
ingestr/src/appstore/__init__.py
ingestr/src/appstore/client.py
ingestr/src/appstore/errors.py
ingestr/src/appstore/models.py
ingestr/src/appstore/resources.py
ingestr/src/arrow/__init__.py
ingestr/src/asana_source/__init__.py
ingestr/src/asana_source/helpers.py
ingestr/src/asana_source/settings.py
ingestr/src/attio/__init__.py
ingestr/src/attio/helpers.py
ingestr/src/bruin/__init__.py
ingestr/src/chess/__init__.py
ingestr/src/chess/helpers.py
ingestr/src/chess/settings.py
ingestr/src/clickup/__init__.py
ingestr/src/clickup/helpers.py
ingestr/src/collector/spinner.py
ingestr/src/couchbase_source/__init__.py
ingestr/src/couchbase_source/helpers.py
ingestr/src/cursor/__init__.py
ingestr/src/cursor/helpers.py
ingestr/src/customer_io/__init__.py
ingestr/src/customer_io/helpers.py
ingestr/src/docebo/__init__.py
ingestr/src/docebo/client.py
ingestr/src/docebo/helpers.py
ingestr/src/dynamodb/__init__.py
ingestr/src/elasticsearch/__init__.py
ingestr/src/elasticsearch/helpers.py
ingestr/src/facebook_ads/__init__.py
ingestr/src/facebook_ads/exceptions.py
ingestr/src/facebook_ads/helpers.py
ingestr/src/facebook_ads/settings.py
ingestr/src/facebook_ads/utils.py
ingestr/src/filesystem/__init__.py
ingestr/src/filesystem/helpers.py
ingestr-0.14.126.dist-info/METADATA
ingestr-0.14.126.dist-info/WHEEL
ingestr-0.14.126.dist-info/entry_points.txt
ingestr-0.14.126.dist-info/licenses/LICENSE.Apache-2.0
ingestr-0.14.126.dist-info/licenses/LICENSE.md
ingestr-0.14.126.dist-info/licenses/NOTICE
ingestr-0.14.126.dist-info/RECORD
